setupy/__init__.py
setupy/__main__.py
setupy/help.py
setupy/setupy.py
setupy/core/__init__.py
setupy/core/feature.py
setupy/core/model.py
setupy/core/serialize.py
setupy/core/setting.py
setupy/errors/__init__.py
setupy/loaders/__init__.py
setupy/loaders/file_loader.py
setupy/loaders/yaml_loader.py
setupy/server/__init__.py
setupy/server/app.py
setupy-0.6.0.dist-info/METADATA
setupy-0.6.0.dist-info/WHEEL
setupy-0.6.0.dist-info/top_level.txt
setupy-0.6.0.dist-info/RECORD
