Metadata-Version: 2.1
Name: setupy
Version: 0.6.0
Summary: UNKNOWN
Home-page: UNKNOWN
License: UNKNOWN
Platform: UNKNOWN
Requires-Dist: isort (>=4.3)
Requires-Dist: pyyaml (>=3.13)
Requires-Dist: flask (>=1.0.2)
Provides-Extra: dev
Requires-Dist: pytest ; extra == 'dev'
Requires-Dist: pytest-cov ; extra == 'dev'
Provides-Extra: neovim
Requires-Dist: neovim ; extra == 'neovim'
